vk_captchasolver/__init__.py
vk_captchasolver/captcha_model.onnx
vk_captchasolver/ctc_model.onnx
vk_captchasolver/vk_captchasolver.py
vk_captchasolver-1.0.4.dist-info/LICENSE
vk_captchasolver-1.0.4.dist-info/METADATA
vk_captchasolver-1.0.4.dist-info/WHEEL
vk_captchasolver-1.0.4.dist-info/top_level.txt
vk_captchasolver-1.0.4.dist-info/RECORD
