Metadata-Version: 2.1
Name: vk-captchasolver
Version: 1.0.4
Summary: VKontakte captcha solver with 91% accuracy right.
Home-page: https://github.com/DedInc/vk_captchasolver
Author: Maehdakvan
Author-email: visitanimation@google.com
License: UNKNOWN
Project-URL: Bug Tracker, https://github.com/DedInc/vk_captchasolver/issues
Platform: UNKNOWN
Classifier: Programming Language :: Python :: 3
Classifier: License :: OSI Approved :: MIT License
Classifier: Operating System :: OS Independent
Requires-Python: >=3.6
License-File: LICENSE
